dasy/__init__.py
dasy/core.py
dasy/plotting_utils.py
dasy/labelers/__init__.py
dasy/labelers/classification/__init__.py
dasy/labelers/classification/centroids.py
dasy/labelers/regression/__init__.py
dasy/labelers/regression/linear.py
dasy/synthesizers/__init__.py
dasy/synthesizers/gaussian.py
dasy/synthesizers/uniform.py
tests/__init__.py
tests/test_classification_labelers.py
tests/test_quickstart.py
tests/test_regression_labelers.py
tests/test_synthesizers.py
dasy_ml-0.0.5.dist-info/LICENSE
dasy_ml-0.0.5.dist-info/METADATA
dasy_ml-0.0.5.dist-info/WHEEL
dasy_ml-0.0.5.dist-info/top_level.txt
dasy_ml-0.0.5.dist-info/RECORD
