Metadata-Version: 2.1
Name: dasy-ml
Version: 0.0.5
Summary: DaSy DataSynthesizer - Create synthetic data for machine learning research
Home-page: https://github.com/bkestelman/dasy-ml
Author: Benito Kestelman
Author-email: bkestelman@outlook.com
License: UNKNOWN
Project-URL: Bug Tracker, https://github.com/bkestelman/dasy-ml/issues
Platform: UNKNOWN
Classifier: Programming Language :: Python :: 3
Classifier: License :: OSI Approved :: MIT License
Classifier: Operating System :: OS Independent
Requires-Python: >=3.6
License-File: LICENSE
Requires-Dist: numpy
